ankra/__init__.py
ankra-0.0.1.dist-info/LICENSE
ankra-0.0.1.dist-info/METADATA
ankra-0.0.1.dist-info/WHEEL
ankra-0.0.1.dist-info/top_level.txt
ankra-0.0.1.dist-info/RECORD
