Metadata-Version: 2.1
Name: ankra
Version: 0.0.1
Summary: A small example package
Home-page: https://github.com/lhjnilsson/ankra
Author: lhjnilsson
Author-email: henrik@lhjnilsson.com
License: UNKNOWN
Platform: UNKNOWN
Classifier: Programming Language :: Python :: 3
Classifier: License :: OSI Approved :: MIT License
Classifier: Operating System :: OS Independent
Requires-Python: >=3.6
